factom_keys/__init__.py
factom_keys/ec.py
factom_keys/fct.py
factom_keys-0.0.2.dist-info/LICENSE
factom_keys-0.0.2.dist-info/METADATA
factom_keys-0.0.2.dist-info/WHEEL
factom_keys-0.0.2.dist-info/top_level.txt
factom_keys-0.0.2.dist-info/RECORD
